{
  "project_info": {
    "project_number": "469691587213",
    "firebase_url": "https://dagcoin-test.firebaseio.com",
    "project_id": "dagcoin-test",
    "storage_bucket": "dagcoin-test.appspot.com"
  },
  "client": [
    {
      "client_info": {
        "mobilesdk_app_id": "1:469691587213:android:a9dfe99517bc1e67",
        "android_client_info": {
          "package_name": "com.scotchio.slickshot"
        }
      },
      "oauth_client": [
        {
          "client_id": "469691587213-6gpb95asdu64c6mnu5ho1dn48m1si9jr.apps.googleusercontent.com",
          "client_type": 3
        }
      ],
      "api_key": [
        {
          "current_key": "AIzaSyB_uXfRP2Szlk1DpvKoZPz43FbXiCBfhdg"
        }
      ],
      "services": {
        "analytics_service": {
          "status": 1
        },
        "appinvite_service": {
          "status": 1,
          "other_platform_oauth_client": []
        },
        "ads_service": {
          "status": 2
        }
      }
    },
    {
      "client_info": {
        "mobilesdk_app_id": "1:469691587213:android:4ee747e290a6a0be",
        "android_client_info": {
          "package_name": "org.dagcoin"
        }
      },
      "oauth_client": [
        {
          "client_id": "469691587213-6gpb95asdu64c6mnu5ho1dn48m1si9jr.apps.googleusercontent.com",
          "client_type": 3
        }
      ],
      "api_key": [
        {
          "current_key": "AIzaSyB_uXfRP2Szlk1DpvKoZPz43FbXiCBfhdg"
        }
      ],
      "services": {
        "analytics_service": {
          "status": 1
        },
        "appinvite_service": {
          "status": 1,
          "other_platform_oauth_client": []
        },
        "ads_service": {
          "status": 2
        }
      }
    }
  ],
  "configuration_version": "1"
}
